mdp_core/__init__.py
mdp_core/client/__init__.py
mdp_core/client/async_mongo_client.py
mdp_core/client/async_rabbit_client.py
mdp_core/client/async_redis_client.py
mdp_core/exception/__init__.py
mdp_core/exception/exceptions.py
mdp_core/lib/__init__.py
mdp_core/lib/cfg.py
mdp_core/lib/func.py
mdp_core/lib/logger.py
mdp_core/lib/notify.py
mdp_core/lib/secret.py
mdp_core/lib/settings.py
mdp_core/lib/time.py
mdp_core/lib/util.py
mdp_core/utils/__init__.py
mdp_core/utils/common.py
mdp_core/utils/decator.py
mdp_core/utils/encryption.py
mdp_core/utils/sequence.py
mdp_core/web/__init__.py
mdp_core/web/aiohttp_client.py
mdp_core/web/curl_cffi_client.py
mdp_core/web/proxy.py
mdp_core-0.0.3.dist-info/METADATA
mdp_core-0.0.3.dist-info/WHEEL
mdp_core-0.0.3.dist-info/top_level.txt
mdp_core-0.0.3.dist-info/RECORD
